LICENSE
gracy/__init__.py
gracy/_configs.py
gracy/_core.py
gracy/_general.py
gracy/_loggers.py
gracy/_models.py
gracy/_paginator.py
gracy/_reports/_builders.py
gracy/_reports/_models.py
gracy/_reports/_printers.py
gracy/_types.py
gracy/_validators.py
gracy/common_hooks.py
gracy/exceptions.py
gracy/py.typed
gracy/replays/_wrappers.py
gracy/replays/storages/_base.py
gracy/replays/storages/_sqlite_schema.py
gracy/replays/storages/pymongo.py
gracy/replays/storages/sqlite.py
gracy-1.34.0.dist-info/LICENSE
gracy-1.34.0.dist-info/METADATA
gracy-1.34.0.dist-info/WHEEL
gracy-1.34.0.dist-info/RECORD
