Metadata-Version: 2.1
Name: gracy
Version: 1.34.0
Summary: Gracefully manage your API interactions
Home-page: https://github.com/guilatrova/gracy
License: MIT
Keywords: api,throttling,http,https,async,retry
Author: Guilherme Latrova
Author-email: hello@guilatrova.dev
Requires-Python: >=3.8.1,<4.0
Classifier: Development Status :: 4 - Beta
Classifier: Environment :: Web Environment
Classifier: Framework :: AsyncIO
Classifier: Intended Audience :: Developers
Classifier: License :: OSI Approved :: BSD License
Classifier: License :: OSI Approved :: MIT License
Classifier: Operating System :: OS Independent
Classifier: Programming Language :: Python :: 3
Classifier: Programming Language :: Python :: 3.9
Classifier: Programming Language :: Python :: 3.10
Classifier: Programming Language :: Python :: 3.11
Classifier: Programming Language :: Python :: 3.12
Classifier: Programming Language :: Python :: 3.13
Classifier: Programming Language :: Python :: 3 :: Only
Classifier: Programming Language :: Python :: 3.8
Classifier: Topic :: Internet :: WWW/HTTP
Provides-Extra: plotly
Provides-Extra: pymongo
Provides-Extra: rich
Requires-Dist: httpx (>=0.23.0)
Requires-Dist: pymongo ; extra == "pymongo"
Requires-Dist: rich ; extra == "rich"
Requires-Dist: typing-extensions (>=4.9.0,<5.0.0)
Project-URL: Changelog, https://github.com/guilatrova/gracy/blob/main/CHANGELOG.md
Project-URL: Repository, https://github.com/guilatrova/gracy
